zammad_py/__init__.py
zammad_py/api.py
zammad_py/exceptions.py
zammad_py-3.2.0.dist-info/LICENSE
zammad_py-3.2.0.dist-info/METADATA
zammad_py-3.2.0.dist-info/WHEEL
zammad_py-3.2.0.dist-info/RECORD
