Metadata-Version: 2.1
Name: zammad_py
Version: 3.2.0
Summary: Python API client for zammad
Home-page: https://github.com/joeirimpan/zammad_py
License: MIT
Author: Joe Paul
Author-email: joeirimpan@gmail.com
Requires-Python: >=3.9,<4.0
Classifier: Development Status :: 4 - Beta
Classifier: Intended Audience :: Developers
Classifier: License :: OSI Approved :: MIT License
Classifier: Natural Language :: English
Classifier: Programming Language :: Python :: 3
Classifier: Programming Language :: Python :: 3.9
Classifier: Programming Language :: Python :: 3.10
Classifier: Programming Language :: Python :: 3.11
Classifier: Programming Language :: Python :: 3.12
Requires-Dist: requests (>=2.25.1,<3.0.0)
Project-URL: Documentation, https://zammad-py.readthedocs.io/
Project-URL: Repository, https://github.com/joeirimpan/zammad_py.git
